Metadata-Version: 2.1
Name: htmlq
Version: 0.1.8
Summary: Script that enables querying an html input (file or url) as using jquery selector strings
Home-page: https://github.com/dealfonso/htmlq
Author: Carlos A.
Author-email: caralla@upv.es
License: Apache 2.0
Keywords: html,command line,htmlquery,jquery,url
Platform: UNKNOWN
Classifier: Development Status :: 4 - Beta
Classifier: Intended Audience :: Developers
Classifier: Intended Audience :: System Administrators
Classifier: Topic :: Utilities
Classifier: License :: OSI Approved :: Apache Software License
Classifier: Programming Language :: Python :: 3
